{"meta":{"builtAt":"2026-07-15","source":"Dubai Land Department open data (2025)"},"areas":{"WADI AL SAFA 4":{"2025-01":{"n":179,"offplan":178},"2025-02":{"n":123,"offplan":123},"2025-03":{"n":36,"offplan":36},"2025-04":{"n":31,"offplan":31},"2025-05":{"n":16,"offplan":15},"2025-06":{"n":112,"offplan":111},"2025-07":{"n":379,"offplan":379},"2025-08":{"n":341,"offplan":341},"2025-09":{"n":219,"offplan":219},"2025-10":{"n":127,"offplan":127},"2025-11":{"n":202,"offplan":202},"2025-12":{"n":56,"offplan":56}},"DUBAI SCIENCE PARK":{"2025-01":{"n":148,"offplan":142},"2025-02":{"n":214,"offplan":205},"2025-03":{"n":219,"offplan":205},"2025-04":{"n":110,"offplan":89},"2025-05":{"n":163,"offplan":151},"2025-06":{"n":234,"offplan":215},"2025-07":{"n":562,"offplan":531},"2025-08":{"n":738,"offplan":701},"2025-09":{"n":1375,"offplan":1360},"2025-10":{"n":789,"offplan":766},"2025-11":{"n":439,"offplan":413},"2025-12":{"n":285,"offplan":277}},"AL FURJAN":{"2025-01":{"n":300,"offplan":180},"2025-02":{"n":228,"offplan":103},"2025-03":{"n":256,"offplan":145},"2025-04":{"n":310,"offplan":203},"2025-05":{"n":338,"offplan":214},"2025-06":{"n":283,"offplan":171},"2025-07":{"n":330,"offplan":223},"2025-08":{"n":327,"offplan":214},"2025-09":{"n":257,"offplan":172},"2025-10":{"n":237,"offplan":119},"2025-11":{"n":221,"offplan":123},"2025-12":{"n":147,"offplan":75}},"AL BARARI":{"2025-01":{"n":497,"offplan":487},"2025-02":{"n":564,"offplan":554},"2025-03":{"n":309,"offplan":298},"2025-04":{"n":183,"offplan":175},"2025-05":{"n":113,"offplan":102},"2025-06":{"n":68,"offplan":63},"2025-07":{"n":50,"offplan":46},"2025-08":{"n":97,"offplan":89},"2025-09":{"n":43,"offplan":41},"2025-10":{"n":141,"offplan":129},"2025-11":{"n":329,"offplan":320},"2025-12":{"n":174,"offplan":164}},"JUMEIRAH VILLAGE TRIANGLE":{"2025-01":{"n":224,"offplan":176},"2025-02":{"n":161,"offplan":131},"2025-03":{"n":119,"offplan":87},"2025-04":{"n":303,"offplan":248},"2025-05":{"n":411,"offplan":343},"2025-06":{"n":350,"offplan":286},"2025-07":{"n":382,"offplan":314},"2025-08":{"n":338,"offplan":279},"2025-09":{"n":502,"offplan":446},"2025-10":{"n":927,"offplan":852},"2025-11":{"n":865,"offplan":788},"2025-12":{"n":398,"offplan":359}},"DUBAI LAND RESIDENCE COMPLEX":{"2025-01":{"n":771,"offplan":640},"2025-02":{"n":618,"offplan":499},"2025-03":{"n":492,"offplan":372},"2025-04":{"n":648,"offplan":545},"2025-05":{"n":567,"offplan":447},"2025-06":{"n":569,"offplan":475},"2025-07":{"n":626,"offplan":537},"2025-08":{"n":613,"offplan":517},"2025-09":{"n":768,"offplan":703},"2025-10":{"n":881,"offplan":799},"2025-11":{"n":751,"offplan":677},"2025-12":{"n":440,"offplan":399}},"BUSINESS BAY":{"2025-01":{"n":742,"offplan":395},"2025-02":{"n":863,"offplan":394},"2025-03":{"n":1126,"offplan":717},"2025-04":{"n":1186,"offplan":629},"2025-05":{"n":1045,"offplan":618},"2025-06":{"n":929,"offplan":550},"2025-07":{"n":1431,"offplan":997},"2025-08":{"n":1744,"offplan":1396},"2025-09":{"n":1429,"offplan":1078},"2025-10":{"n":1153,"offplan":710},"2025-11":{"n":1084,"offplan":673},"2025-12":{"n":820,"offplan":506}},"SOBHA HEARTLAND":{"2025-01":{"n":87,"offplan":39},"2025-02":{"n":87,"offplan":31},"2025-03":{"n":95,"offplan":29},"2025-04":{"n":109,"offplan":42},"2025-05":{"n":114,"offplan":24},"2025-06":{"n":92,"offplan":34},"2025-07":{"n":136,"offplan":10},"2025-08":{"n":108,"offplan":12},"2025-09":{"n":88,"offplan":16},"2025-10":{"n":120,"offplan":26},"2025-11":{"n":113,"offplan":21},"2025-12":{"n":86,"offplan":22}},"JUMEIRAH FIRST":{"2025-01":{"n":2,"offplan":2},"2025-02":{"n":7,"offplan":7},"2025-03":{"n":2,"offplan":2},"2025-04":{"n":8,"offplan":8},"2025-05":{"n":22,"offplan":22},"2025-06":{"n":10,"offplan":10},"2025-07":{"n":2,"offplan":2},"2025-08":{"n":3,"offplan":3},"2025-10":{"n":4,"offplan":4},"2025-11":{"n":44,"offplan":44},"2025-12":{"n":12,"offplan":12}},"MADINAT AL MATAAR":{"2025-01":{"n":319,"offplan":319},"2025-02":{"n":594,"offplan":582},"2025-03":{"n":605,"offplan":591},"2025-04":{"n":713,"offplan":702},"2025-05":{"n":576,"offplan":558},"2025-06":{"n":437,"offplan":423},"2025-07":{"n":479,"offplan":458},"2025-08":{"n":577,"offplan":533},"2025-09":{"n":682,"offplan":646},"2025-10":{"n":411,"offplan":378},"2025-11":{"n":755,"offplan":731},"2025-12":{"n":604,"offplan":587}},"AL YUFRAH 1":{"2025-01":{"n":160,"offplan":155},"2025-02":{"n":402,"offplan":395},"2025-03":{"n":317,"offplan":310},"2025-04":{"n":130,"offplan":127},"2025-05":{"n":237,"offplan":232},"2025-06":{"n":187,"offplan":179},"2025-07":{"n":119,"offplan":110},"2025-08":{"n":52,"offplan":48},"2025-09":{"n":54,"offplan":45},"2025-10":{"n":297,"offplan":282},"2025-11":{"n":309,"offplan":288},"2025-12":{"n":58,"offplan":54}},"JUMEIRAH VILLAGE CIRCLE":{"2025-01":{"n":951,"offplan":584},"2025-02":{"n":1232,"offplan":772},"2025-03":{"n":1359,"offplan":927},"2025-04":{"n":1606,"offplan":1160},"2025-05":{"n":1830,"offplan":1244},"2025-06":{"n":1469,"offplan":1061},"2025-07":{"n":1845,"offplan":1068},"2025-08":{"n":1597,"offplan":1179},"2025-09":{"n":2109,"offplan":1652},"2025-10":{"n":1636,"offplan":1126},"2025-11":{"n":1462,"offplan":1029},"2025-12":{"n":1048,"offplan":685}},"DUBAI MARITIME CITY":{"2025-01":{"n":118,"offplan":115},"2025-02":{"n":187,"offplan":184},"2025-03":{"n":152,"offplan":148},"2025-04":{"n":56,"offplan":54},"2025-05":{"n":64,"offplan":62},"2025-06":{"n":79,"offplan":75},"2025-07":{"n":327,"offplan":316},"2025-08":{"n":312,"offplan":299},"2025-09":{"n":325,"offplan":322},"2025-10":{"n":274,"offplan":271},"2025-11":{"n":724,"offplan":719},"2025-12":{"n":308,"offplan":300}},"DUBAI PRODUCTION CITY":{"2025-01":{"n":149,"offplan":53},"2025-02":{"n":288,"offplan":169},"2025-03":{"n":615,"offplan":516},"2025-04":{"n":843,"offplan":734},"2025-05":{"n":562,"offplan":444},"2025-06":{"n":325,"offplan":242},"2025-07":{"n":545,"offplan":448},"2025-08":{"n":601,"offplan":519},"2025-09":{"n":470,"offplan":405},"2025-10":{"n":375,"offplan":280},"2025-11":{"n":284,"offplan":193},"2025-12":{"n":216,"offplan":155}},"MADINAT HIND 4":{"2025-01":{"n":71,"offplan":54},"2025-02":{"n":53,"offplan":38},"2025-03":{"n":23,"offplan":7},"2025-04":{"n":25,"offplan":9},"2025-05":{"n":24,"offplan":8},"2025-06":{"n":29,"offplan":13},"2025-07":{"n":24,"offplan":8},"2025-08":{"n":26,"offplan":10},"2025-09":{"n":21,"offplan":7},"2025-10":{"n":28,"offplan":7},"2025-11":{"n":22,"offplan":4},"2025-12":{"n":10,"offplan":3}},"HADAEQ SHEIKH MOHAMMED BIN RASHID":{"2025-01":{"n":152,"offplan":152},"2025-02":{"n":277,"offplan":277},"2025-03":{"n":203,"offplan":203},"2025-04":{"n":288,"offplan":288},"2025-05":{"n":198,"offplan":197},"2025-06":{"n":182,"offplan":181},"2025-07":{"n":318,"offplan":318},"2025-08":{"n":371,"offplan":371},"2025-09":{"n":195,"offplan":193},"2025-10":{"n":121,"offplan":121},"2025-11":{"n":210,"offplan":207},"2025-12":{"n":130,"offplan":129}},"JABAL ALI FIRST":{"2025-01":{"n":200,"offplan":193},"2025-02":{"n":221,"offplan":212},"2025-03":{"n":87,"offplan":82},"2025-04":{"n":266,"offplan":258},"2025-05":{"n":121,"offplan":112},"2025-06":{"n":106,"offplan":99},"2025-07":{"n":63,"offplan":55},"2025-08":{"n":199,"offplan":195},"2025-09":{"n":102,"offplan":100},"2025-10":{"n":142,"offplan":135},"2025-11":{"n":134,"offplan":129},"2025-12":{"n":114,"offplan":112}},"DUBAI SPORTS CITY":{"2025-01":{"n":191,"offplan":71},"2025-02":{"n":202,"offplan":84},"2025-03":{"n":356,"offplan":241},"2025-04":{"n":235,"offplan":113},"2025-05":{"n":256,"offplan":112},"2025-06":{"n":314,"offplan":192},"2025-07":{"n":254,"offplan":107},"2025-08":{"n":353,"offplan":218},"2025-09":{"n":335,"offplan":146},"2025-10":{"n":368,"offplan":206},"2025-11":{"n":472,"offplan":278},"2025-12":{"n":269,"offplan":152}},"MAJAN":{"2025-01":{"n":161,"offplan":150},"2025-02":{"n":255,"offplan":223},"2025-03":{"n":111,"offplan":91},"2025-04":{"n":202,"offplan":171},"2025-05":{"n":189,"offplan":163},"2025-06":{"n":229,"offplan":220},"2025-07":{"n":382,"offplan":328},"2025-08":{"n":479,"offplan":403},"2025-09":{"n":457,"offplan":375},"2025-10":{"n":341,"offplan":265},"2025-11":{"n":284,"offplan":219},"2025-12":{"n":540,"offplan":498}},"BUKADRA":{"2025-01":{"n":180,"offplan":180},"2025-02":{"n":277,"offplan":277},"2025-03":{"n":181,"offplan":181},"2025-04":{"n":313,"offplan":313},"2025-05":{"n":481,"offplan":481},"2025-06":{"n":359,"offplan":359},"2025-07":{"n":713,"offplan":713},"2025-08":{"n":312,"offplan":312},"2025-09":{"n":290,"offplan":290},"2025-10":{"n":217,"offplan":217},"2025-11":{"n":192,"offplan":192},"2025-12":{"n":70,"offplan":70}},"DOWNTOWN DUBAI":{"2025-01":{"n":360,"offplan":102},"2025-02":{"n":352,"offplan":90},"2025-03":{"n":337,"offplan":97},"2025-04":{"n":356,"offplan":132},"2025-05":{"n":364,"offplan":142},"2025-06":{"n":254,"offplan":58},"2025-07":{"n":284,"offplan":63},"2025-08":{"n":249,"offplan":65},"2025-09":{"n":243,"offplan":60},"2025-10":{"n":438,"offplan":231},"2025-11":{"n":496,"offplan":273},"2025-12":{"n":225,"offplan":92}},"DUBAI MARINA":{"2025-01":{"n":437,"offplan":194},"2025-02":{"n":522,"offplan":261},"2025-03":{"n":781,"offplan":485},"2025-04":{"n":752,"offplan":493},"2025-05":{"n":580,"offplan":305},"2025-06":{"n":413,"offplan":182},"2025-07":{"n":440,"offplan":214},"2025-08":{"n":334,"offplan":146},"2025-09":{"n":349,"offplan":137},"2025-10":{"n":297,"offplan":77},"2025-11":{"n":319,"offplan":83},"2025-12":{"n":208,"offplan":62}},"ARJAN":{"2025-01":{"n":224,"offplan":140},"2025-02":{"n":289,"offplan":187},"2025-03":{"n":237,"offplan":156},"2025-04":{"n":371,"offplan":279},"2025-05":{"n":333,"offplan":169},"2025-06":{"n":255,"offplan":156},"2025-07":{"n":312,"offplan":172},"2025-08":{"n":205,"offplan":118},"2025-09":{"n":321,"offplan":200},"2025-10":{"n":340,"offplan":194},"2025-11":{"n":503,"offplan":326},"2025-12":{"n":334,"offplan":242}},"DUBAI STUDIO CITY":{"2025-01":{"n":137,"offplan":130},"2025-02":{"n":148,"offplan":134},"2025-03":{"n":87,"offplan":76},"2025-04":{"n":270,"offplan":255},"2025-05":{"n":255,"offplan":239},"2025-06":{"n":301,"offplan":290},"2025-07":{"n":223,"offplan":209},"2025-08":{"n":130,"offplan":113},"2025-09":{"n":228,"offplan":217},"2025-10":{"n":302,"offplan":286},"2025-11":{"n":293,"offplan":129},"2025-12":{"n":88,"offplan":61}},"MEYDAN AVENUE":{"2025-01":{"n":20,"offplan":11},"2025-02":{"n":24,"offplan":3},"2025-03":{"n":42,"offplan":1},"2025-04":{"n":8,"offplan":0},"2025-05":{"n":19,"offplan":0},"2025-06":{"n":29,"offplan":0},"2025-07":{"n":30,"offplan":0},"2025-08":{"n":14,"offplan":0},"2025-09":{"n":12,"offplan":0},"2025-10":{"n":15,"offplan":0},"2025-11":{"n":26,"offplan":2},"2025-12":{"n":18,"offplan":6}},"JUMEIRAH LAKES TOWERS":{"2025-01":{"n":445,"offplan":208},"2025-02":{"n":407,"offplan":193},"2025-03":{"n":390,"offplan":185},"2025-04":{"n":334,"offplan":156},"2025-05":{"n":440,"offplan":174},"2025-06":{"n":391,"offplan":153},"2025-07":{"n":369,"offplan":128},"2025-08":{"n":389,"offplan":179},"2025-09":{"n":294,"offplan":122},"2025-10":{"n":327,"offplan":127},"2025-11":{"n":316,"offplan":118},"2025-12":{"n":210,"offplan":64}},"RAS AL KHOR INDUSTRIAL FIRST":{"2025-01":{"n":24,"offplan":24},"2025-02":{"n":72,"offplan":72},"2025-03":{"n":38,"offplan":38},"2025-04":{"n":51,"offplan":51},"2025-05":{"n":114,"offplan":114},"2025-06":{"n":100,"offplan":100},"2025-07":{"n":87,"offplan":87},"2025-08":{"n":64,"offplan":64},"2025-09":{"n":45,"offplan":45},"2025-10":{"n":42,"offplan":42},"2025-11":{"n":52,"offplan":52},"2025-12":{"n":24,"offplan":24}},"SILICON OASIS":{"2025-01":{"n":260,"offplan":151},"2025-02":{"n":372,"offplan":248},"2025-03":{"n":317,"offplan":202},"2025-04":{"n":351,"offplan":217},"2025-05":{"n":377,"offplan":226},"2025-06":{"n":453,"offplan":339},"2025-07":{"n":309,"offplan":189},"2025-08":{"n":341,"offplan":234},"2025-09":{"n":411,"offplan":246},"2025-10":{"n":385,"offplan":212},"2025-11":{"n":373,"offplan":211},"2025-12":{"n":163,"offplan":80}},"PALM JUMEIRAH":{"2025-01":{"n":105,"offplan":26},"2025-02":{"n":104,"offplan":17},"2025-03":{"n":126,"offplan":22},"2025-04":{"n":146,"offplan":33},"2025-05":{"n":122,"offplan":17},"2025-06":{"n":122,"offplan":20},"2025-07":{"n":115,"offplan":48},"2025-08":{"n":76,"offplan":19},"2025-09":{"n":136,"offplan":52},"2025-10":{"n":144,"offplan":61},"2025-11":{"n":150,"offplan":67},"2025-12":{"n":91,"offplan":20}},"DAMAC HILLS":{"2025-01":{"n":72,"offplan":16},"2025-02":{"n":67,"offplan":22},"2025-03":{"n":75,"offplan":10},"2025-04":{"n":120,"offplan":14},"2025-05":{"n":150,"offplan":22},"2025-06":{"n":103,"offplan":41},"2025-07":{"n":80,"offplan":19},"2025-08":{"n":57,"offplan":6},"2025-09":{"n":136,"offplan":87},"2025-10":{"n":200,"offplan":150},"2025-11":{"n":286,"offplan":204},"2025-12":{"n":88,"offplan":56}},"DUBAI WATER CANAL":{"2025-01":{"n":28,"offplan":17},"2025-02":{"n":42,"offplan":31},"2025-03":{"n":53,"offplan":7},"2025-04":{"n":81,"offplan":20},"2025-05":{"n":70,"offplan":17},"2025-06":{"n":27,"offplan":16},"2025-07":{"n":27,"offplan":11},"2025-08":{"n":16,"offplan":7},"2025-09":{"n":20,"offplan":13},"2025-10":{"n":21,"offplan":6},"2025-11":{"n":20,"offplan":9},"2025-12":{"n":15,"offplan":8}},"MOTOR CITY":{"2025-01":{"n":126,"offplan":66},"2025-02":{"n":341,"offplan":267},"2025-03":{"n":476,"offplan":403},"2025-04":{"n":342,"offplan":254},"2025-05":{"n":602,"offplan":531},"2025-06":{"n":762,"offplan":700},"2025-07":{"n":656,"offplan":586},"2025-08":{"n":529,"offplan":453},"2025-09":{"n":634,"offplan":464},"2025-10":{"n":660,"offplan":496},"2025-11":{"n":675,"offplan":515},"2025-12":{"n":244,"offplan":178}},"DUBAI HARBOUR":{"2025-01":{"n":62,"offplan":30},"2025-02":{"n":51,"offplan":26},"2025-03":{"n":88,"offplan":51},"2025-04":{"n":51,"offplan":22},"2025-05":{"n":79,"offplan":35},"2025-06":{"n":52,"offplan":19},"2025-07":{"n":47,"offplan":16},"2025-08":{"n":37,"offplan":15},"2025-09":{"n":25,"offplan":14},"2025-10":{"n":51,"offplan":21},"2025-11":{"n":36,"offplan":9},"2025-12":{"n":37,"offplan":3}},"TECOM SITE A":{"2025-01":{"n":13,"offplan":12},"2025-02":{"n":62,"offplan":57},"2025-03":{"n":24,"offplan":17},"2025-04":{"n":19,"offplan":12},"2025-05":{"n":16,"offplan":16},"2025-06":{"n":21,"offplan":14},"2025-07":{"n":24,"offplan":19},"2025-08":{"n":10,"offplan":5},"2025-09":{"n":13,"offplan":9},"2025-10":{"n":244,"offplan":19},"2025-11":{"n":35,"offplan":26},"2025-12":{"n":6,"offplan":3}},"MADINAT DUBAI ALMELAHEYAH":{"2025-01":{"n":173,"offplan":173},"2025-02":{"n":128,"offplan":128},"2025-03":{"n":342,"offplan":342},"2025-04":{"n":219,"offplan":219},"2025-05":{"n":218,"offplan":218},"2025-06":{"n":235,"offplan":235},"2025-07":{"n":100,"offplan":100},"2025-08":{"n":244,"offplan":244},"2025-09":{"n":264,"offplan":264},"2025-10":{"n":138,"offplan":138},"2025-11":{"n":253,"offplan":253},"2025-12":{"n":108,"offplan":108}},"AL KIFAF":{"2025-01":{"n":85,"offplan":75},"2025-02":{"n":38,"offplan":28},"2025-03":{"n":20,"offplan":7},"2025-04":{"n":51,"offplan":13},"2025-05":{"n":78,"offplan":65},"2025-06":{"n":68,"offplan":56},"2025-07":{"n":25,"offplan":19},"2025-08":{"n":190,"offplan":184},"2025-09":{"n":98,"offplan":90},"2025-10":{"n":27,"offplan":16},"2025-11":{"n":34,"offplan":23},"2025-12":{"n":55,"offplan":49}},"LIWAN":{"2025-01":{"n":64,"offplan":35},"2025-02":{"n":41,"offplan":10},"2025-03":{"n":78,"offplan":22},"2025-04":{"n":103,"offplan":44},"2025-05":{"n":76,"offplan":30},"2025-06":{"n":112,"offplan":65},"2025-07":{"n":149,"offplan":100},"2025-08":{"n":76,"offplan":26},"2025-09":{"n":115,"offplan":74},"2025-10":{"n":81,"offplan":28},"2025-11":{"n":88,"offplan":47},"2025-12":{"n":122,"offplan":96}},"WADI AL SAFA 7":{"2025-01":{"n":130,"offplan":93},"2025-02":{"n":236,"offplan":212},"2025-03":{"n":126,"offplan":108},"2025-04":{"n":104,"offplan":78},"2025-05":{"n":76,"offplan":57},"2025-06":{"n":134,"offplan":97},"2025-07":{"n":101,"offplan":38},"2025-08":{"n":94,"offplan":42},"2025-09":{"n":103,"offplan":51},"2025-10":{"n":115,"offplan":74},"2025-11":{"n":77,"offplan":36},"2025-12":{"n":31,"offplan":14}},"PALM DEIRA":{"2025-01":{"n":88,"offplan":88},"2025-02":{"n":278,"offplan":278},"2025-03":{"n":323,"offplan":323},"2025-04":{"n":426,"offplan":426},"2025-05":{"n":394,"offplan":394},"2025-06":{"n":385,"offplan":385},"2025-07":{"n":294,"offplan":294},"2025-08":{"n":207,"offplan":207},"2025-09":{"n":457,"offplan":457},"2025-10":{"n":456,"offplan":456},"2025-11":{"n":496,"offplan":496},"2025-12":{"n":326,"offplan":326}},"SUFOUH GARDENS":{"2025-01":{"n":17,"offplan":7},"2025-02":{"n":13,"offplan":4},"2025-03":{"n":18,"offplan":8},"2025-04":{"n":8,"offplan":0},"2025-05":{"n":9,"offplan":1},"2025-06":{"n":20,"offplan":11},"2025-07":{"n":32,"offplan":19},"2025-08":{"n":11,"offplan":7},"2025-09":{"n":9,"offplan":2},"2025-10":{"n":22,"offplan":13},"2025-11":{"n":8,"offplan":0},"2025-12":{"n":16,"offplan":13}},"AL SATWA":{"2025-01":{"n":69,"offplan":69},"2025-02":{"n":46,"offplan":46},"2025-03":{"n":89,"offplan":89},"2025-04":{"n":83,"offplan":83},"2025-05":{"n":119,"offplan":119},"2025-06":{"n":143,"offplan":136},"2025-07":{"n":124,"offplan":120},"2025-08":{"n":173,"offplan":168},"2025-09":{"n":106,"offplan":100},"2025-10":{"n":117,"offplan":110},"2025-11":{"n":112,"offplan":101},"2025-12":{"n":42,"offplan":40}},"TECOM SITE D":{"2025-01":{"n":89,"offplan":89},"2025-02":{"n":250,"offplan":250},"2025-03":{"n":49,"offplan":49},"2025-04":{"n":44,"offplan":44},"2025-05":{"n":18,"offplan":18},"2025-06":{"n":44,"offplan":44},"2025-07":{"n":100,"offplan":100},"2025-08":{"n":13,"offplan":13},"2025-09":{"n":9,"offplan":9},"2025-10":{"n":4,"offplan":4},"2025-11":{"n":3,"offplan":3},"2025-12":{"n":2,"offplan":2}},"HORIZON":{"2025-01":{"n":148,"offplan":148},"2025-02":{"n":59,"offplan":59},"2025-03":{"n":21,"offplan":21},"2025-04":{"n":41,"offplan":41},"2025-05":{"n":19,"offplan":19},"2025-06":{"n":29,"offplan":29},"2025-07":{"n":61,"offplan":61},"2025-08":{"n":48,"offplan":48},"2025-09":{"n":211,"offplan":211},"2025-10":{"n":84,"offplan":84},"2025-11":{"n":203,"offplan":203},"2025-12":{"n":83,"offplan":83}},"THE LAKES":{"2025-01":{"n":14,"offplan":5},"2025-02":{"n":14,"offplan":5},"2025-03":{"n":10,"offplan":6},"2025-04":{"n":17,"offplan":7},"2025-05":{"n":12,"offplan":7},"2025-06":{"n":12,"offplan":3},"2025-07":{"n":9,"offplan":5},"2025-08":{"n":7,"offplan":2},"2025-09":{"n":18,"offplan":8},"2025-10":{"n":9,"offplan":3},"2025-11":{"n":13,"offplan":4},"2025-12":{"n":5,"offplan":2}},"MBR DISTRICT 1":{"2025-01":{"n":12,"offplan":1},"2025-02":{"n":20,"offplan":1},"2025-03":{"n":23,"offplan":1},"2025-04":{"n":19,"offplan":2},"2025-05":{"n":19,"offplan":0},"2025-06":{"n":22,"offplan":0},"2025-07":{"n":23,"offplan":0},"2025-08":{"n":12,"offplan":0},"2025-09":{"n":11,"offplan":0},"2025-10":{"n":15,"offplan":0},"2025-11":{"n":23,"offplan":0},"2025-12":{"n":6,"offplan":0}},"AL HEBIAH SIXTH":{"2025-01":{"n":24,"offplan":24},"2025-02":{"n":18,"offplan":18},"2025-03":{"n":14,"offplan":14},"2025-04":{"n":16,"offplan":16},"2025-05":{"n":26,"offplan":26},"2025-06":{"n":23,"offplan":22},"2025-07":{"n":17,"offplan":14},"2025-08":{"n":37,"offplan":24},"2025-09":{"n":43,"offplan":17},"2025-10":{"n":56,"offplan":24},"2025-11":{"n":63,"offplan":22},"2025-12":{"n":37,"offplan":9}},"AL YELAYISS 2":{"2025-01":{"n":138,"offplan":126},"2025-02":{"n":153,"offplan":144},"2025-03":{"n":98,"offplan":88},"2025-04":{"n":113,"offplan":99},"2025-05":{"n":190,"offplan":181},"2025-06":{"n":94,"offplan":82},"2025-07":{"n":149,"offplan":108},"2025-08":{"n":211,"offplan":153},"2025-09":{"n":176,"offplan":132},"2025-10":{"n":113,"offplan":73},"2025-11":{"n":217,"offplan":186},"2025-12":{"n":93,"offplan":78}},"DUBAI HILLS":{"2025-01":{"n":128,"offplan":42},"2025-02":{"n":124,"offplan":39},"2025-03":{"n":165,"offplan":30},"2025-04":{"n":175,"offplan":46},"2025-05":{"n":185,"offplan":37},"2025-06":{"n":134,"offplan":33},"2025-07":{"n":124,"offplan":20},"2025-08":{"n":94,"offplan":13},"2025-09":{"n":113,"offplan":28},"2025-10":{"n":160,"offplan":25},"2025-11":{"n":105,"offplan":19},"2025-12":{"n":78,"offplan":10}},"DUBAI SOUTH":{"2025-01":{"n":561,"offplan":502},"2025-02":{"n":150,"offplan":91},"2025-03":{"n":261,"offplan":220},"2025-04":{"n":127,"offplan":72},"2025-05":{"n":112,"offplan":44},"2025-06":{"n":111,"offplan":47},"2025-07":{"n":188,"offplan":103},"2025-08":{"n":165,"offplan":105},"2025-09":{"n":216,"offplan":123},"2025-10":{"n":240,"offplan":111},"2025-11":{"n":118,"offplan":65},"2025-12":{"n":131,"offplan":34}},"DUBAI CREEK HARBOUR":{"2025-01":{"n":145,"offplan":31},"2025-02":{"n":222,"offplan":100},"2025-03":{"n":136,"offplan":28},"2025-04":{"n":177,"offplan":25},"2025-05":{"n":207,"offplan":42},"2025-06":{"n":134,"offplan":17},"2025-07":{"n":141,"offplan":27},"2025-08":{"n":157,"offplan":26},"2025-09":{"n":139,"offplan":29},"2025-10":{"n":145,"offplan":13},"2025-11":{"n":194,"offplan":21},"2025-12":{"n":104,"offplan":9}},"MEYDAN ONE":{"2025-01":{"n":139,"offplan":36},"2025-02":{"n":125,"offplan":28},"2025-03":{"n":133,"offplan":23},"2025-04":{"n":236,"offplan":30},"2025-05":{"n":175,"offplan":14},"2025-06":{"n":122,"offplan":7},"2025-07":{"n":112,"offplan":13},"2025-08":{"n":94,"offplan":9},"2025-09":{"n":143,"offplan":30},"2025-10":{"n":135,"offplan":11},"2025-11":{"n":137,"offplan":9},"2025-12":{"n":68,"offplan":9}},"DUBAI INVESTMENT PARK SECOND":{"2025-01":{"n":69,"offplan":48},"2025-02":{"n":68,"offplan":53},"2025-03":{"n":21,"offplan":8},"2025-04":{"n":32,"offplan":14},"2025-05":{"n":60,"offplan":33},"2025-06":{"n":350,"offplan":339},"2025-07":{"n":811,"offplan":789},"2025-08":{"n":880,"offplan":864},"2025-09":{"n":868,"offplan":851},"2025-10":{"n":745,"offplan":732},"2025-11":{"n":580,"offplan":570},"2025-12":{"n":793,"offplan":779}},"MINA RASHID":{"2025-01":{"n":1,"offplan":1},"2025-02":{"n":1,"offplan":1},"2025-03":{"n":3,"offplan":3},"2025-04":{"n":1,"offplan":1},"2025-05":{"n":4,"offplan":0},"2025-06":{"n":6,"offplan":0},"2025-07":{"n":1,"offplan":0},"2025-08":{"n":1,"offplan":0},"2025-09":{"n":1,"offplan":0},"2025-10":{"n":2,"offplan":0},"2025-12":{"n":4,"offplan":0}},"JADDAF WATERFRONT":{"2025-01":{"n":31,"offplan":18},"2025-02":{"n":107,"offplan":93},"2025-03":{"n":139,"offplan":125},"2025-04":{"n":56,"offplan":48},"2025-05":{"n":128,"offplan":109},"2025-06":{"n":84,"offplan":69},"2025-07":{"n":107,"offplan":95},"2025-08":{"n":88,"offplan":84},"2025-09":{"n":147,"offplan":137},"2025-10":{"n":142,"offplan":131},"2025-11":{"n":168,"offplan":160},"2025-12":{"n":84,"offplan":71}},"WADI AL SAFA 3":{"2025-01":{"n":42,"offplan":30},"2025-02":{"n":64,"offplan":61},"2025-03":{"n":71,"offplan":67},"2025-04":{"n":81,"offplan":75},"2025-05":{"n":78,"offplan":70},"2025-06":{"n":68,"offplan":62},"2025-07":{"n":71,"offplan":67},"2025-08":{"n":86,"offplan":77},"2025-09":{"n":102,"offplan":95},"2025-10":{"n":78,"offplan":65},"2025-11":{"n":64,"offplan":47},"2025-12":{"n":31,"offplan":26}},"VILLANOVA":{"2025-01":{"n":31,"offplan":4},"2025-02":{"n":32,"offplan":5},"2025-03":{"n":34,"offplan":2},"2025-04":{"n":45,"offplan":6},"2025-05":{"n":33,"offplan":3},"2025-06":{"n":27,"offplan":1},"2025-07":{"n":25,"offplan":2},"2025-08":{"n":18,"offplan":0},"2025-09":{"n":23,"offplan":0},"2025-10":{"n":22,"offplan":0},"2025-11":{"n":27,"offplan":0},"2025-12":{"n":17,"offplan":0}},"UM SUQAIM THIRD":{"2025-01":{"n":19,"offplan":19},"2025-02":{"n":19,"offplan":19},"2025-03":{"n":19,"offplan":17},"2025-04":{"n":22,"offplan":15},"2025-05":{"n":40,"offplan":33},"2025-06":{"n":27,"offplan":20},"2025-07":{"n":14,"offplan":10},"2025-08":{"n":10,"offplan":4},"2025-09":{"n":17,"offplan":14},"2025-10":{"n":21,"offplan":15},"2025-11":{"n":40,"offplan":33},"2025-12":{"n":21,"offplan":14}},"TOWN SQUARE":{"2025-01":{"n":67,"offplan":11},"2025-02":{"n":80,"offplan":8},"2025-03":{"n":83,"offplan":1},"2025-04":{"n":79,"offplan":4},"2025-05":{"n":111,"offplan":16},"2025-06":{"n":81,"offplan":3},"2025-07":{"n":86,"offplan":2},"2025-08":{"n":61,"offplan":2},"2025-09":{"n":69,"offplan":6},"2025-10":{"n":79,"offplan":6},"2025-11":{"n":79,"offplan":6},"2025-12":{"n":62,"offplan":4}},"AL KHAIRAN FIRST":{"2025-01":{"n":23,"offplan":23},"2025-02":{"n":22,"offplan":22},"2025-03":{"n":15,"offplan":15},"2025-04":{"n":86,"offplan":86},"2025-05":{"n":318,"offplan":318},"2025-06":{"n":269,"offplan":269},"2025-07":{"n":217,"offplan":217},"2025-08":{"n":160,"offplan":160},"2025-09":{"n":277,"offplan":277},"2025-10":{"n":130,"offplan":130},"2025-11":{"n":369,"offplan":369},"2025-12":{"n":79,"offplan":79}},"AL WASL":{"2025-01":{"n":21,"offplan":19},"2025-02":{"n":21,"offplan":20},"2025-03":{"n":45,"offplan":42},"2025-04":{"n":287,"offplan":282},"2025-05":{"n":251,"offplan":248},"2025-06":{"n":167,"offplan":164},"2025-07":{"n":105,"offplan":103},"2025-08":{"n":132,"offplan":131},"2025-09":{"n":127,"offplan":124},"2025-10":{"n":172,"offplan":165},"2025-11":{"n":60,"offplan":53},"2025-12":{"n":39,"offplan":36}},"DOWN TOWN JABAL ALI":{"2025-01":{"n":38,"offplan":24},"2025-02":{"n":65,"offplan":51},"2025-03":{"n":85,"offplan":65},"2025-04":{"n":91,"offplan":64},"2025-05":{"n":80,"offplan":52},"2025-06":{"n":51,"offplan":39},"2025-07":{"n":99,"offplan":80},"2025-08":{"n":72,"offplan":61},"2025-09":{"n":40,"offplan":28},"2025-10":{"n":36,"offplan":19},"2025-11":{"n":34,"offplan":15},"2025-12":{"n":48,"offplan":30}},"WADI AL SAFA 2":{"2025-01":{"n":9,"offplan":9},"2025-02":{"n":6,"offplan":6},"2025-03":{"n":7,"offplan":7},"2025-04":{"n":10,"offplan":10},"2025-05":{"n":10,"offplan":10},"2025-06":{"n":8,"offplan":8},"2025-07":{"n":22,"offplan":22},"2025-08":{"n":18,"offplan":18},"2025-09":{"n":21,"offplan":21},"2025-10":{"n":29,"offplan":29},"2025-11":{"n":22,"offplan":22},"2025-12":{"n":6,"offplan":6}},"THE FIELD":{"2025-01":{"n":14,"offplan":5},"2025-02":{"n":11,"offplan":2},"2025-03":{"n":23,"offplan":4},"2025-04":{"n":17,"offplan":5},"2025-05":{"n":9,"offplan":3},"2025-06":{"n":17,"offplan":3},"2025-07":{"n":27,"offplan":8},"2025-08":{"n":10,"offplan":1},"2025-09":{"n":3,"offplan":1},"2025-10":{"n":13,"offplan":0},"2025-11":{"n":18,"offplan":0},"2025-12":{"n":6,"offplan":0}},"AL MERKADH":{"2025-01":{"n":4,"offplan":4},"2025-02":{"n":8,"offplan":8},"2025-03":{"n":7,"offplan":7},"2025-04":{"n":7,"offplan":7},"2025-05":{"n":13,"offplan":13},"2025-06":{"n":10,"offplan":10},"2025-07":{"n":8,"offplan":8},"2025-08":{"n":5,"offplan":5},"2025-09":{"n":12,"offplan":12},"2025-10":{"n":11,"offplan":11},"2025-11":{"n":8,"offplan":8},"2025-12":{"n":8,"offplan":8}},"LIVING LEGENDS":{"2025-01":{"n":8,"offplan":4},"2025-02":{"n":13,"offplan":11},"2025-03":{"n":5,"offplan":2},"2025-04":{"n":8,"offplan":5},"2025-05":{"n":20,"offplan":19},"2025-06":{"n":12,"offplan":9},"2025-07":{"n":26,"offplan":23},"2025-08":{"n":18,"offplan":8},"2025-09":{"n":21,"offplan":13},"2025-10":{"n":30,"offplan":12},"2025-11":{"n":39,"offplan":19},"2025-12":{"n":53,"offplan":45}},"NAD AL SHIBA FIRST":{"2025-01":{"n":3,"offplan":3},"2025-02":{"n":93,"offplan":92},"2025-03":{"n":44,"offplan":44},"2025-04":{"n":12,"offplan":12},"2025-05":{"n":11,"offplan":11},"2025-06":{"n":11,"offplan":11},"2025-07":{"n":5,"offplan":5},"2025-08":{"n":5,"offplan":5},"2025-09":{"n":34,"offplan":33},"2025-10":{"n":126,"offplan":126},"2025-11":{"n":31,"offplan":31},"2025-12":{"n":23,"offplan":23}},"THE WORLD":{"2025-01":{"n":6,"offplan":5},"2025-02":{"n":6,"offplan":6},"2025-03":{"n":12,"offplan":10},"2025-04":{"n":4,"offplan":3},"2025-05":{"n":15,"offplan":10},"2025-06":{"n":13,"offplan":11},"2025-07":{"n":15,"offplan":14},"2025-08":{"n":11,"offplan":11},"2025-09":{"n":13,"offplan":10},"2025-11":{"n":3,"offplan":2},"2025-12":{"n":1,"offplan":1}},"ZAABEEL FIRST":{"2025-01":{"n":12,"offplan":7},"2025-02":{"n":19,"offplan":11},"2025-03":{"n":6,"offplan":0},"2025-04":{"n":6,"offplan":4},"2025-05":{"n":25,"offplan":21},"2025-06":{"n":12,"offplan":11},"2025-07":{"n":11,"offplan":10},"2025-08":{"n":11,"offplan":7},"2025-09":{"n":8,"offplan":7},"2025-10":{"n":17,"offplan":9},"2025-11":{"n":6,"offplan":3},"2025-12":{"n":3,"offplan":0}},"CITY WALK":{"2025-01":{"n":25,"offplan":8},"2025-02":{"n":29,"offplan":8},"2025-03":{"n":20,"offplan":8},"2025-04":{"n":19,"offplan":5},"2025-05":{"n":24,"offplan":6},"2025-06":{"n":26,"offplan":7},"2025-07":{"n":19,"offplan":10},"2025-08":{"n":16,"offplan":5},"2025-09":{"n":23,"offplan":2},"2025-10":{"n":12,"offplan":2},"2025-11":{"n":20,"offplan":4},"2025-12":{"n":15,"offplan":3}},"JUMEIRAH GOLF":{"2025-01":{"n":6,"offplan":1},"2025-02":{"n":18,"offplan":0},"2025-03":{"n":13,"offplan":0},"2025-04":{"n":15,"offplan":0},"2025-05":{"n":19,"offplan":0},"2025-06":{"n":9,"offplan":0},"2025-07":{"n":16,"offplan":0},"2025-08":{"n":4,"offplan":0},"2025-09":{"n":16,"offplan":0},"2025-10":{"n":40,"offplan":0},"2025-11":{"n":14,"offplan":0},"2025-12":{"n":7,"offplan":0}},"CITY OF ARABIA":{"2025-01":{"n":32,"offplan":32},"2025-02":{"n":12,"offplan":12},"2025-03":{"n":19,"offplan":18},"2025-04":{"n":150,"offplan":150},"2025-05":{"n":48,"offplan":48},"2025-06":{"n":15,"offplan":13},"2025-07":{"n":40,"offplan":39},"2025-08":{"n":36,"offplan":36},"2025-09":{"n":45,"offplan":45},"2025-10":{"n":110,"offplan":110},"2025-11":{"n":73,"offplan":73},"2025-12":{"n":54,"offplan":53}},"AL JADAF":{"2025-01":{"n":9,"offplan":9},"2025-02":{"n":10,"offplan":10},"2025-03":{"n":55,"offplan":55},"2025-04":{"n":42,"offplan":42},"2025-05":{"n":63,"offplan":63},"2025-06":{"n":50,"offplan":50},"2025-07":{"n":40,"offplan":40},"2025-08":{"n":155,"offplan":155},"2025-09":{"n":170,"offplan":170},"2025-10":{"n":65,"offplan":65},"2025-11":{"n":97,"offplan":97},"2025-12":{"n":60,"offplan":60}},"INTERNATIONAL CITY PH 2 3":{"2025-01":{"n":58,"offplan":19},"2025-02":{"n":136,"offplan":56},"2025-03":{"n":125,"offplan":64},"2025-04":{"n":120,"offplan":53},"2025-05":{"n":107,"offplan":49},"2025-06":{"n":232,"offplan":99},"2025-07":{"n":153,"offplan":94},"2025-08":{"n":200,"offplan":144},"2025-09":{"n":130,"offplan":97},"2025-10":{"n":159,"offplan":112},"2025-11":{"n":130,"offplan":99},"2025-12":{"n":71,"offplan":46}},"EMAAR SOUTH":{"2025-01":{"n":26,"offplan":1},"2025-02":{"n":40,"offplan":3},"2025-03":{"n":39,"offplan":10},"2025-04":{"n":41,"offplan":1},"2025-05":{"n":47,"offplan":16},"2025-06":{"n":43,"offplan":17},"2025-07":{"n":23,"offplan":2},"2025-08":{"n":19,"offplan":2},"2025-09":{"n":19,"offplan":2},"2025-10":{"n":29,"offplan":3},"2025-11":{"n":39,"offplan":1},"2025-12":{"n":17,"offplan":2}},"AL KHAIL HEIGHTS":{"2025-01":{"n":16,"offplan":0},"2025-02":{"n":11,"offplan":0},"2025-03":{"n":10,"offplan":0},"2025-04":{"n":24,"offplan":0},"2025-05":{"n":16,"offplan":0},"2025-06":{"n":18,"offplan":0},"2025-07":{"n":13,"offplan":0},"2025-08":{"n":18,"offplan":0},"2025-09":{"n":17,"offplan":0},"2025-10":{"n":14,"offplan":0},"2025-11":{"n":17,"offplan":0},"2025-12":{"n":11,"offplan":0}},"LA MER":{"2025-01":{"n":20,"offplan":0},"2025-02":{"n":16,"offplan":0},"2025-03":{"n":20,"offplan":0},"2025-04":{"n":31,"offplan":0},"2025-05":{"n":24,"offplan":0},"2025-06":{"n":13,"offplan":0},"2025-07":{"n":18,"offplan":0},"2025-08":{"n":7,"offplan":0},"2025-09":{"n":12,"offplan":0},"2025-10":{"n":19,"offplan":0},"2025-11":{"n":14,"offplan":0},"2025-12":{"n":26,"offplan":15}},"BARSHA HEIGHTS":{"2025-01":{"n":58,"offplan":0},"2025-02":{"n":45,"offplan":2},"2025-03":{"n":27,"offplan":0},"2025-04":{"n":55,"offplan":14},"2025-05":{"n":53,"offplan":24},"2025-06":{"n":51,"offplan":13},"2025-07":{"n":51,"offplan":18},"2025-08":{"n":49,"offplan":12},"2025-09":{"n":37,"offplan":8},"2025-10":{"n":32,"offplan":4},"2025-11":{"n":34,"offplan":1},"2025-12":{"n":35,"offplan":0}},"MIRA":{"2025-01":{"n":42,"offplan":0},"2025-02":{"n":51,"offplan":0},"2025-03":{"n":41,"offplan":0},"2025-04":{"n":33,"offplan":0},"2025-05":{"n":20,"offplan":0},"2025-06":{"n":23,"offplan":0},"2025-07":{"n":20,"offplan":0},"2025-08":{"n":15,"offplan":0},"2025-09":{"n":14,"offplan":0},"2025-10":{"n":25,"offplan":0},"2025-11":{"n":22,"offplan":0},"2025-12":{"n":11,"offplan":0}},"REMRAAM":{"2025-01":{"n":45,"offplan":0},"2025-02":{"n":28,"offplan":0},"2025-03":{"n":31,"offplan":0},"2025-04":{"n":47,"offplan":0},"2025-05":{"n":60,"offplan":0},"2025-06":{"n":44,"offplan":0},"2025-07":{"n":40,"offplan":0},"2025-08":{"n":35,"offplan":0},"2025-09":{"n":34,"offplan":0},"2025-10":{"n":44,"offplan":0},"2025-11":{"n":29,"offplan":0},"2025-12":{"n":21,"offplan":0}},"DISCOVERY GARDENS":{"2025-01":{"n":63,"offplan":0},"2025-02":{"n":74,"offplan":0},"2025-03":{"n":75,"offplan":0},"2025-04":{"n":79,"offplan":0},"2025-05":{"n":93,"offplan":0},"2025-06":{"n":69,"offplan":0},"2025-07":{"n":101,"offplan":0},"2025-08":{"n":63,"offplan":0},"2025-09":{"n":74,"offplan":0},"2025-10":{"n":76,"offplan":0},"2025-11":{"n":73,"offplan":0},"2025-12":{"n":56,"offplan":0}},"INTERNATIONAL CITY PH 1":{"2025-01":{"n":139,"offplan":0},"2025-02":{"n":267,"offplan":0},"2025-03":{"n":180,"offplan":0},"2025-04":{"n":154,"offplan":0},"2025-05":{"n":184,"offplan":0},"2025-06":{"n":136,"offplan":0},"2025-07":{"n":182,"offplan":0},"2025-08":{"n":156,"offplan":0},"2025-09":{"n":189,"offplan":1},"2025-10":{"n":161,"offplan":14},"2025-11":{"n":207,"offplan":20},"2025-12":{"n":104,"offplan":11}},"THE GREENS":{"2025-01":{"n":57,"offplan":0},"2025-02":{"n":60,"offplan":0},"2025-03":{"n":56,"offplan":0},"2025-04":{"n":52,"offplan":0},"2025-05":{"n":73,"offplan":0},"2025-06":{"n":58,"offplan":0},"2025-07":{"n":59,"offplan":0},"2025-08":{"n":40,"offplan":0},"2025-09":{"n":48,"offplan":0},"2025-10":{"n":57,"offplan":0},"2025-11":{"n":55,"offplan":0},"2025-12":{"n":31,"offplan":0}},"RUKAN":{"2025-01":{"n":7,"offplan":0},"2025-02":{"n":4,"offplan":0},"2025-03":{"n":1,"offplan":0},"2025-04":{"n":1,"offplan":0},"2025-05":{"n":1,"offplan":0},"2025-06":{"n":3,"offplan":0},"2025-07":{"n":3,"offplan":0},"2025-08":{"n":2,"offplan":0},"2025-09":{"n":4,"offplan":0},"2025-10":{"n":3,"offplan":0},"2025-11":{"n":5,"offplan":0}},"JUMEIRAH BEACH RESIDENCE":{"2025-01":{"n":60,"offplan":0},"2025-02":{"n":55,"offplan":0},"2025-03":{"n":59,"offplan":0},"2025-04":{"n":72,"offplan":0},"2025-05":{"n":62,"offplan":0},"2025-06":{"n":43,"offplan":0},"2025-07":{"n":39,"offplan":0},"2025-08":{"n":50,"offplan":0},"2025-09":{"n":52,"offplan":0},"2025-10":{"n":59,"offplan":0},"2025-11":{"n":70,"offplan":0},"2025-12":{"n":29,"offplan":0}},"SERENA":{"2025-01":{"n":7,"offplan":0},"2025-02":{"n":13,"offplan":0},"2025-03":{"n":12,"offplan":0},"2025-04":{"n":17,"offplan":0},"2025-05":{"n":14,"offplan":0},"2025-06":{"n":11,"offplan":0},"2025-07":{"n":13,"offplan":0},"2025-08":{"n":8,"offplan":0},"2025-09":{"n":10,"offplan":0},"2025-10":{"n":9,"offplan":0},"2025-11":{"n":3,"offplan":0},"2025-12":{"n":3,"offplan":0}},"ME AISEM FIRST":{"2025-01":{"n":2,"offplan":0},"2025-02":{"n":3,"offplan":0},"2025-03":{"n":2,"offplan":0},"2025-04":{"n":1,"offplan":1},"2025-06":{"n":3,"offplan":0},"2025-07":{"n":2,"offplan":0},"2025-08":{"n":2,"offplan":0},"2025-09":{"n":2,"offplan":0},"2025-10":{"n":2,"offplan":1},"2025-11":{"n":5,"offplan":3},"2025-12":{"n":3,"offplan":2}},"CHERRYWOODS":{"2025-01":{"n":5,"offplan":0},"2025-02":{"n":2,"offplan":0},"2025-03":{"n":3,"offplan":0},"2025-04":{"n":4,"offplan":0},"2025-05":{"n":6,"offplan":0},"2025-07":{"n":4,"offplan":0},"2025-08":{"n":3,"offplan":0},"2025-09":{"n":2,"offplan":0},"2025-10":{"n":1,"offplan":0},"2025-12":{"n":2,"offplan":0}},"AL KHEERAN":{"2025-01":{"n":4,"offplan":0},"2025-02":{"n":13,"offplan":0},"2025-03":{"n":6,"offplan":0},"2025-04":{"n":4,"offplan":0},"2025-05":{"n":11,"offplan":0},"2025-06":{"n":7,"offplan":0},"2025-07":{"n":5,"offplan":0},"2025-08":{"n":6,"offplan":0},"2025-09":{"n":7,"offplan":0},"2025-10":{"n":7,"offplan":0},"2025-11":{"n":2,"offplan":0},"2025-12":{"n":2,"offplan":0}},"MBR DISTRICT 7":{"2025-01":{"n":25,"offplan":0},"2025-02":{"n":35,"offplan":0},"2025-03":{"n":29,"offplan":0},"2025-04":{"n":30,"offplan":0},"2025-05":{"n":21,"offplan":0},"2025-06":{"n":13,"offplan":0},"2025-07":{"n":19,"offplan":0},"2025-08":{"n":7,"offplan":0},"2025-09":{"n":13,"offplan":0},"2025-10":{"n":13,"offplan":0},"2025-11":{"n":8,"offplan":0},"2025-12":{"n":12,"offplan":0}},"DUBAI HEALTHCARE CITY PHASE 2":{"2025-01":{"n":19,"offplan":0},"2025-02":{"n":33,"offplan":4},"2025-03":{"n":59,"offplan":33},"2025-04":{"n":70,"offplan":30},"2025-05":{"n":38,"offplan":9},"2025-06":{"n":45,"offplan":21},"2025-07":{"n":119,"offplan":89},"2025-08":{"n":110,"offplan":80},"2025-09":{"n":48,"offplan":32},"2025-10":{"n":65,"offplan":31},"2025-11":{"n":102,"offplan":52},"2025-12":{"n":80,"offplan":36}},"ARABIAN RANCHES I":{"2025-01":{"n":16,"offplan":0},"2025-02":{"n":12,"offplan":0},"2025-03":{"n":16,"offplan":0},"2025-04":{"n":12,"offplan":0},"2025-05":{"n":16,"offplan":0},"2025-06":{"n":16,"offplan":0},"2025-07":{"n":13,"offplan":0},"2025-08":{"n":24,"offplan":0},"2025-09":{"n":16,"offplan":0},"2025-10":{"n":19,"offplan":0},"2025-11":{"n":15,"offplan":0},"2025-12":{"n":15,"offplan":0}},"EMIRATE LIVING":{"2025-01":{"n":45,"offplan":0},"2025-02":{"n":33,"offplan":0},"2025-03":{"n":37,"offplan":0},"2025-04":{"n":43,"offplan":0},"2025-05":{"n":39,"offplan":0},"2025-06":{"n":43,"offplan":0},"2025-07":{"n":34,"offplan":0},"2025-08":{"n":34,"offplan":0},"2025-09":{"n":43,"offplan":0},"2025-10":{"n":44,"offplan":0},"2025-11":{"n":39,"offplan":0},"2025-12":{"n":28,"offplan":0}},"JUMEIRAH LIVING":{"2025-01":{"n":6,"offplan":0},"2025-02":{"n":3,"offplan":0},"2025-03":{"n":12,"offplan":0},"2025-04":{"n":10,"offplan":0},"2025-05":{"n":1,"offplan":0},"2025-06":{"n":12,"offplan":0},"2025-07":{"n":5,"offplan":0},"2025-08":{"n":3,"offplan":0},"2025-09":{"n":3,"offplan":0},"2025-10":{"n":8,"offplan":0},"2025-11":{"n":5,"offplan":0},"2025-12":{"n":5,"offplan":0}},"WARSAN FIRST":{"2025-01":{"n":6,"offplan":0},"2025-02":{"n":8,"offplan":1},"2025-03":{"n":9,"offplan":4},"2025-04":{"n":10,"offplan":4},"2025-05":{"n":11,"offplan":3},"2025-06":{"n":7,"offplan":3},"2025-07":{"n":8,"offplan":5},"2025-08":{"n":9,"offplan":6},"2025-09":{"n":8,"offplan":5},"2025-10":{"n":5,"offplan":3},"2025-11":{"n":4,"offplan":0},"2025-12":{"n":5,"offplan":0}},"AL WAHA":{"2025-01":{"n":4,"offplan":0},"2025-02":{"n":4,"offplan":0},"2025-03":{"n":4,"offplan":0},"2025-04":{"n":3,"offplan":0},"2025-05":{"n":4,"offplan":0},"2025-06":{"n":4,"offplan":0},"2025-07":{"n":4,"offplan":0},"2025-09":{"n":1,"offplan":0},"2025-10":{"n":1,"offplan":0},"2025-12":{"n":1,"offplan":0}},"ARABIAN RANCHES III":{"2025-01":{"n":15,"offplan":0},"2025-02":{"n":22,"offplan":0},"2025-03":{"n":16,"offplan":0},"2025-04":{"n":28,"offplan":0},"2025-05":{"n":34,"offplan":0},"2025-06":{"n":19,"offplan":0},"2025-07":{"n":30,"offplan":0},"2025-08":{"n":15,"offplan":0},"2025-09":{"n":12,"offplan":0},"2025-10":{"n":21,"offplan":0},"2025-11":{"n":14,"offplan":0},"2025-12":{"n":5,"offplan":0}},"DUBAI INDUSTRIAL CITY":{"2025-01":{"n":8,"offplan":0},"2025-02":{"n":8,"offplan":0},"2025-03":{"n":5,"offplan":0},"2025-04":{"n":75,"offplan":12},"2025-05":{"n":24,"offplan":16},"2025-06":{"n":21,"offplan":15},"2025-07":{"n":223,"offplan":219},"2025-08":{"n":198,"offplan":189},"2025-09":{"n":188,"offplan":188},"2025-10":{"n":87,"offplan":81},"2025-11":{"n":45,"offplan":42},"2025-12":{"n":59,"offplan":55}},"TILAL AL GHAF":{"2025-01":{"n":6,"offplan":0},"2025-02":{"n":6,"offplan":0},"2025-03":{"n":8,"offplan":0},"2025-04":{"n":7,"offplan":0},"2025-05":{"n":8,"offplan":0},"2025-06":{"n":5,"offplan":0},"2025-07":{"n":4,"offplan":0},"2025-08":{"n":9,"offplan":0},"2025-09":{"n":5,"offplan":0},"2025-10":{"n":7,"offplan":0},"2025-11":{"n":5,"offplan":0},"2025-12":{"n":6,"offplan":0}},"ZAABEEL SECOND":{"2025-01":{"n":23,"offplan":0},"2025-02":{"n":21,"offplan":0},"2025-03":{"n":16,"offplan":0},"2025-04":{"n":12,"offplan":0},"2025-05":{"n":16,"offplan":0},"2025-06":{"n":14,"offplan":0},"2025-07":{"n":187,"offplan":164},"2025-08":{"n":99,"offplan":86},"2025-09":{"n":78,"offplan":67},"2025-10":{"n":75,"offplan":59},"2025-11":{"n":29,"offplan":14},"2025-12":{"n":16,"offplan":11}},"DUBAI WATER FRONT":{"2025-01":{"n":3,"offplan":0},"2025-04":{"n":1,"offplan":0},"2025-05":{"n":4,"offplan":0},"2025-06":{"n":6,"offplan":0},"2025-07":{"n":1,"offplan":0},"2025-08":{"n":1,"offplan":0},"2025-09":{"n":2,"offplan":0},"2025-10":{"n":1,"offplan":0},"2025-11":{"n":5,"offplan":0},"2025-12":{"n":2,"offplan":0}},"BLUEWATERS":{"2025-01":{"n":10,"offplan":0},"2025-02":{"n":16,"offplan":0},"2025-03":{"n":9,"offplan":0},"2025-04":{"n":7,"offplan":0},"2025-05":{"n":5,"offplan":0},"2025-06":{"n":7,"offplan":0},"2025-07":{"n":4,"offplan":0},"2025-08":{"n":7,"offplan":0},"2025-09":{"n":4,"offplan":0},"2025-10":{"n":6,"offplan":0},"2025-11":{"n":12,"offplan":0},"2025-12":{"n":10,"offplan":0}},"JUMEIRA BAY":{"2025-01":{"n":2,"offplan":0},"2025-03":{"n":1,"offplan":0},"2025-04":{"n":5,"offplan":0},"2025-05":{"n":4,"offplan":0},"2025-06":{"n":2,"offplan":0},"2025-09":{"n":1,"offplan":0},"2025-10":{"n":1,"offplan":0},"2025-11":{"n":4,"offplan":0},"2025-12":{"n":1,"offplan":0}},"AL BARSHAA SOUTH THIRD":{"2025-01":{"n":2,"offplan":0},"2025-02":{"n":1,"offplan":0},"2025-03":{"n":1,"offplan":0},"2025-04":{"n":5,"offplan":0},"2025-05":{"n":1,"offplan":0},"2025-06":{"n":1,"offplan":0},"2025-07":{"n":4,"offplan":0},"2025-08":{"n":2,"offplan":0},"2025-09":{"n":2,"offplan":0},"2025-10":{"n":1,"offplan":0},"2025-11":{"n":1,"offplan":0},"2025-12":{"n":1,"offplan":0}},"MUDON":{"2025-01":{"n":5,"offplan":0},"2025-02":{"n":6,"offplan":0},"2025-03":{"n":1,"offplan":0},"2025-04":{"n":6,"offplan":0},"2025-05":{"n":3,"offplan":0},"2025-06":{"n":4,"offplan":0},"2025-07":{"n":6,"offplan":0},"2025-08":{"n":5,"offplan":0},"2025-11":{"n":3,"offplan":0}},"PEARL JUMEIRA":{"2025-01":{"n":1,"offplan":0},"2025-03":{"n":1,"offplan":0},"2025-08":{"n":1,"offplan":0},"2025-10":{"n":1,"offplan":0}},"AL BARSHA FIRST":{"2025-01":{"n":2,"offplan":0},"2025-03":{"n":1,"offplan":0},"2025-04":{"n":6,"offplan":3},"2025-05":{"n":27,"offplan":27},"2025-06":{"n":9,"offplan":4},"2025-07":{"n":5,"offplan":5},"2025-08":{"n":18,"offplan":14},"2025-09":{"n":10,"offplan":10},"2025-10":{"n":14,"offplan":10},"2025-11":{"n":2,"offplan":0},"2025-12":{"n":8,"offplan":7}},"DUBAI HEALTHCARE CITY PHASE 1":{"2025-01":{"n":1,"offplan":0},"2025-04":{"n":2,"offplan":0},"2025-05":{"n":3,"offplan":0},"2025-06":{"n":3,"offplan":2},"2025-09":{"n":2,"offplan":0},"2025-10":{"n":2,"offplan":0},"2025-11":{"n":1,"offplan":0}},"PORT SAEED":{"2025-01":{"n":1,"offplan":0},"2025-02":{"n":1,"offplan":0},"2025-03":{"n":3,"offplan":0},"2025-05":{"n":1,"offplan":0},"2025-06":{"n":3,"offplan":0},"2025-07":{"n":1,"offplan":0},"2025-11":{"n":2,"offplan":0},"2025-12":{"n":1,"offplan":0}},"ARABIAN RANCHES II":{"2025-01":{"n":3,"offplan":0},"2025-02":{"n":2,"offplan":0},"2025-03":{"n":6,"offplan":0},"2025-04":{"n":3,"offplan":0},"2025-05":{"n":7,"offplan":0},"2025-06":{"n":7,"offplan":0},"2025-07":{"n":6,"offplan":0},"2025-08":{"n":4,"offplan":0},"2025-09":{"n":1,"offplan":0},"2025-10":{"n":2,"offplan":0},"2025-11":{"n":3,"offplan":0},"2025-12":{"n":1,"offplan":0}},"JUMEIRAH HEIGHTS":{"2025-01":{"n":4,"offplan":0},"2025-02":{"n":1,"offplan":0},"2025-03":{"n":5,"offplan":1},"2025-04":{"n":169,"offplan":169},"2025-05":{"n":72,"offplan":69},"2025-06":{"n":23,"offplan":16},"2025-07":{"n":34,"offplan":33},"2025-08":{"n":28,"offplan":27},"2025-09":{"n":4,"offplan":4},"2025-10":{"n":76,"offplan":75},"2025-11":{"n":117,"offplan":114},"2025-12":{"n":51,"offplan":50}},"TRADE CENTER FIRST":{"2025-01":{"n":1,"offplan":0},"2025-03":{"n":1,"offplan":0},"2025-04":{"n":6,"offplan":0},"2025-05":{"n":3,"offplan":1},"2025-06":{"n":10,"offplan":6},"2025-07":{"n":213,"offplan":211},"2025-08":{"n":51,"offplan":49},"2025-09":{"n":51,"offplan":51},"2025-10":{"n":36,"offplan":27},"2025-11":{"n":9,"offplan":8},"2025-12":{"n":5,"offplan":1}},"MUHAISANAH FIRST":{"2025-01":{"n":2,"offplan":0},"2025-02":{"n":5,"offplan":0},"2025-03":{"n":2,"offplan":0},"2025-04":{"n":3,"offplan":0},"2025-05":{"n":7,"offplan":0},"2025-06":{"n":2,"offplan":0},"2025-07":{"n":10,"offplan":0},"2025-08":{"n":3,"offplan":0},"2025-09":{"n":3,"offplan":0},"2025-10":{"n":5,"offplan":0},"2025-11":{"n":8,"offplan":0},"2025-12":{"n":2,"offplan":0}},"GRAND VIEWS":{"2025-01":{"n":1,"offplan":0},"2025-02":{"n":2,"offplan":0},"2025-03":{"n":1,"offplan":0},"2025-04":{"n":1,"offplan":0},"2025-05":{"n":3,"offplan":0},"2025-06":{"n":1,"offplan":0},"2025-07":{"n":1,"offplan":0},"2025-08":{"n":2,"offplan":0},"2025-09":{"n":2,"offplan":0},"2025-10":{"n":2,"offplan":0},"2025-11":{"n":2,"offplan":0}},"THE VALLEY":{"2025-01":{"n":7,"offplan":0},"2025-02":{"n":8,"offplan":0},"2025-03":{"n":10,"offplan":0},"2025-04":{"n":16,"offplan":0},"2025-05":{"n":6,"offplan":0},"2025-06":{"n":4,"offplan":0},"2025-07":{"n":10,"offplan":0},"2025-08":{"n":5,"offplan":0},"2025-09":{"n":10,"offplan":0},"2025-10":{"n":15,"offplan":0},"2025-11":{"n":3,"offplan":0},"2025-12":{"n":11,"offplan":0}},"NAD AL HAMAR":{"2025-01":{"n":2,"offplan":0},"2025-02":{"n":2,"offplan":0},"2025-04":{"n":2,"offplan":0},"2025-05":{"n":1,"offplan":0},"2025-06":{"n":16,"offplan":0},"2025-07":{"n":10,"offplan":0},"2025-08":{"n":5,"offplan":0},"2025-09":{"n":3,"offplan":0},"2025-10":{"n":4,"offplan":0},"2025-11":{"n":6,"offplan":0},"2025-12":{"n":2,"offplan":0}},"MIRDIF":{"2025-01":{"n":9,"offplan":0},"2025-02":{"n":10,"offplan":0},"2025-03":{"n":8,"offplan":0},"2025-04":{"n":20,"offplan":0},"2025-05":{"n":13,"offplan":0},"2025-06":{"n":13,"offplan":0},"2025-07":{"n":27,"offplan":13},"2025-08":{"n":12,"offplan":2},"2025-09":{"n":36,"offplan":22},"2025-10":{"n":31,"offplan":17},"2025-11":{"n":21,"offplan":8},"2025-12":{"n":11,"offplan":5}},"DUBAI INVESTMENT PARK FIRST":{"2025-01":{"n":29,"offplan":15},"2025-02":{"n":35,"offplan":10},"2025-03":{"n":27,"offplan":5},"2025-04":{"n":29,"offplan":12},"2025-05":{"n":38,"offplan":10},"2025-06":{"n":38,"offplan":7},"2025-07":{"n":31,"offplan":10},"2025-08":{"n":56,"offplan":24},"2025-09":{"n":24,"offplan":8},"2025-10":{"n":34,"offplan":10},"2025-11":{"n":47,"offplan":18},"2025-12":{"n":27,"offplan":14}},"TRADE CENTER SECOND":{"2025-01":{"n":5,"offplan":0},"2025-02":{"n":2,"offplan":0},"2025-03":{"n":3,"offplan":0},"2025-04":{"n":7,"offplan":0},"2025-05":{"n":5,"offplan":0},"2025-06":{"n":7,"offplan":0},"2025-07":{"n":6,"offplan":0},"2025-08":{"n":240,"offplan":238},"2025-09":{"n":260,"offplan":254},"2025-10":{"n":186,"offplan":180},"2025-11":{"n":32,"offplan":31},"2025-12":{"n":21,"offplan":15}},"NAD AL SHEBA GARDENS":{"2025-02":{"n":2,"offplan":2},"2025-03":{"n":3,"offplan":1},"2025-04":{"n":7,"offplan":6},"2025-05":{"n":13,"offplan":13},"2025-06":{"n":21,"offplan":21},"2025-07":{"n":17,"offplan":17},"2025-08":{"n":2,"offplan":2},"2025-09":{"n":7,"offplan":7},"2025-10":{"n":11,"offplan":11},"2025-11":{"n":13,"offplan":13},"2025-12":{"n":9,"offplan":8}},"DUBAI GOLF CITY":{"2025-02":{"n":1,"offplan":1},"2025-05":{"n":2,"offplan":2},"2025-07":{"n":1,"offplan":1},"2025-08":{"n":1,"offplan":1}},"DUBAI DESIGN DISTRICT":{"2025-02":{"n":2,"offplan":2},"2025-03":{"n":3,"offplan":3},"2025-04":{"n":8,"offplan":8},"2025-05":{"n":2,"offplan":2},"2025-06":{"n":2,"offplan":2},"2025-07":{"n":1,"offplan":1},"2025-08":{"n":1,"offplan":1},"2025-11":{"n":2,"offplan":2},"2025-12":{"n":1,"offplan":1}},"JUMEIRAH SECOND":{"2025-02":{"n":5,"offplan":3},"2025-05":{"n":24,"offplan":24},"2025-06":{"n":26,"offplan":25},"2025-07":{"n":44,"offplan":44},"2025-08":{"n":3,"offplan":3},"2025-09":{"n":20,"offplan":20},"2025-10":{"n":15,"offplan":15},"2025-11":{"n":16,"offplan":15},"2025-12":{"n":3,"offplan":3}},"PALMAROSA":{"2025-02":{"n":1,"offplan":1},"2025-05":{"n":1,"offplan":1},"2025-09":{"n":1,"offplan":1},"2025-11":{"n":1,"offplan":1}},"SUSTAINABLE CITY":{"2025-02":{"n":6,"offplan":0},"2025-03":{"n":16,"offplan":0},"2025-04":{"n":6,"offplan":0},"2025-05":{"n":7,"offplan":0},"2025-06":{"n":4,"offplan":0},"2025-07":{"n":1,"offplan":0},"2025-08":{"n":2,"offplan":0},"2025-09":{"n":1,"offplan":0},"2025-10":{"n":1,"offplan":0},"2025-11":{"n":5,"offplan":0},"2025-12":{"n":4,"offplan":0}},"REGA AL BUTEEN":{"2025-02":{"n":2,"offplan":0},"2025-03":{"n":1,"offplan":0},"2025-04":{"n":1,"offplan":0},"2025-09":{"n":2,"offplan":0},"2025-10":{"n":2,"offplan":0},"2025-12":{"n":1,"offplan":0}},"AL QUSAIS INDUSTRIAL FOURTH":{"2025-02":{"n":1,"offplan":0},"2025-03":{"n":2,"offplan":0},"2025-04":{"n":4,"offplan":0},"2025-05":{"n":1,"offplan":0},"2025-06":{"n":2,"offplan":0},"2025-09":{"n":1,"offplan":0},"2025-11":{"n":1,"offplan":0},"2025-12":{"n":2,"offplan":0}},"BUSINESS PARK":{"2025-03":{"n":7,"offplan":7},"2025-04":{"n":6,"offplan":6},"2025-05":{"n":3,"offplan":3},"2025-06":{"n":1,"offplan":1},"2025-07":{"n":27,"offplan":27},"2025-08":{"n":18,"offplan":18},"2025-09":{"n":22,"offplan":22},"2025-10":{"n":30,"offplan":30},"2025-11":{"n":11,"offplan":11},"2025-12":{"n":9,"offplan":9}},"ISLAND 2":{"2025-03":{"n":1,"offplan":0},"2025-04":{"n":1,"offplan":1},"2025-06":{"n":2,"offplan":2},"2025-10":{"n":1,"offplan":1}},"DMCC EZ2":{"2025-04":{"n":1,"offplan":0},"2025-06":{"n":2,"offplan":0},"2025-07":{"n":2,"offplan":0},"2025-08":{"n":439,"offplan":439},"2025-09":{"n":161,"offplan":160},"2025-10":{"n":309,"offplan":309},"2025-11":{"n":419,"offplan":419},"2025-12":{"n":121,"offplan":116}},"LIWAN 2":{"2025-05":{"n":3,"offplan":3},"2025-06":{"n":2,"offplan":2},"2025-07":{"n":2,"offplan":2},"2025-10":{"n":1,"offplan":1}},"FALCON CITY OF WONDERS":{"2025-06":{"n":142,"offplan":142},"2025-07":{"n":212,"offplan":212},"2025-08":{"n":68,"offplan":68},"2025-09":{"n":61,"offplan":61},"2025-10":{"n":78,"offplan":78},"2025-11":{"n":43,"offplan":43},"2025-12":{"n":15,"offplan":15}},"JUMEIRAH PARK":{"2025-07":{"n":1,"offplan":0},"2025-09":{"n":1,"offplan":0}},"WARSAN FOURTH":{"2025-08":{"n":1,"offplan":1},"2025-09":{"n":2,"offplan":2},"2025-11":{"n":12,"offplan":12},"2025-12":{"n":1,"offplan":1}},"DUBAI LIFESTYLE CITY":{"2025-11":{"n":1,"offplan":1}},"SAIH SHUAIB 2":{"2025-11":{"n":81,"offplan":0}},"AL QUSAIS INDUSTRIAL FIFTH":{"2025-11":{"n":36,"offplan":0},"2025-12":{"n":2,"offplan":0}},"PALM JABAL ALI":{"2025-12":{"n":44,"offplan":44}},"AL YELAYISS 1":{"2025-12":{"n":21,"offplan":21}}}}